mfind/__init__.py
mfind/__main__.py
mfind/argparser.py
mfind/mfind.py
mfind/version.py
tests/test_version.py
mfind-0.0.2.dist-info/LICENSE
mfind-0.0.2.dist-info/METADATA
mfind-0.0.2.dist-info/WHEEL
mfind-0.0.2.dist-info/entry_points.txt
mfind-0.0.2.dist-info/top_level.txt
mfind-0.0.2.dist-info/RECORD
