Metadata-Version: 2.1
Name: mfind
Version: 0.0.2
Summary: Scan a directory for files an apply callbacks on name matches
Home-page: https://github.com/joaompinto/mfind
Author: João Pinto
Author-email: lamego.pinto@gmail.com
License: MIT
Platform: UNKNOWN
